metex/__init__.py
metex/core.py
metex/test/__init__.py
metex/test/test_cli_interface.sh
metex/test/test_library.py
metex-1.2.0.data/scripts/metex
metex-1.2.0.dist-info/LICENSE
metex-1.2.0.dist-info/METADATA
metex-1.2.0.dist-info/WHEEL
metex-1.2.0.dist-info/top_level.txt
metex-1.2.0.dist-info/RECORD
