Metadata-Version: 2.1
Name: metex
Version: 1.2.0
Summary: Maximum Entropy Textures
Home-page: https://gitlab.com/epiasini/metex
Author: Eugenio Piasini
Author-email: eugenio.piasini@gmail.com
License: GPLv3+
Platform: UNKNOWN
Classifier: Development Status :: 4 - Beta
Classifier: Intended Audience :: Science/Research
Classifier: Topic :: Scientific/Engineering
Classifier: License :: OSI Approved :: GNU General Public License v3 or later (GPLv3+)
Classifier: Programming Language :: Python :: 3
Classifier: Operating System :: OS Independent
Classifier: Environment :: Console
Requires-Python: >=3
License-File: LICENSE
Requires-Dist: numpy (>=1.7)
Requires-Dist: matplotlib
